README.txt
setup.py
dist/sgawidgets-1.0a-py2.5.egg
sgawidgets/__init__.py
sgawidgets/release.py
sgawidgets/widgets.py
sgawidgets.egg-info/PKG-INFO
sgawidgets.egg-info/SOURCES.txt
sgawidgets.egg-info/dependency_links.txt
sgawidgets.egg-info/entry_points.txt
sgawidgets.egg-info/not-zip-safe
sgawidgets.egg-info/paster_plugins.txt
sgawidgets.egg-info/requires.txt
sgawidgets.egg-info/sqlobject.txt
sgawidgets.egg-info/top_level.txt
sgawidgets/static/images/favicon.ico
sgawidgets/static/images/tg_under_the_hood.png
sgawidgets/static/images/under_the_hood_blue.png
sgawidgets/static/javascript/ModalPopups.js
sgawidgets/templates/__init__.py
