Metadata-Version: 1.0
Name: sgawidgets
Version: 1.0a
Summary: ModalPopup Widgets collection
Home-page: http://pupilabox.net.ec/index.php?page=widgets_para_turbogears
Author: Patricio Valarezo Lozano
Author-email: patovala@pupilabox.net.ec
License: UNKNOWN
Download-URL: http://pupilabox.net.ec/index.php?page=widgets_para_turbogears
Keywords: turbogears.widgets
Platform: UNKNOWN
Classifier: Development Status :: 3 - Alpha
Classifier: Operating System :: OS Independent
Classifier: Programming Language :: Python
Classifier: Topic :: Software Development :: Libraries :: Python Modules
Classifier: Framework :: TurboGears
Classifier: Framework :: TurboGears :: Applications
Classifier: Framework :: TurboGears :: Widgets
